Workbook

Sheet Price Risk
A2: Quantity | B2: 160000000
A3: Hedge Ratio | B3: 1
A4: Total Volume | B4: =B2*B3 -> 160000000
A5: N | B5: =10*252 -> 2520
A6: Daily Volume | B6: =B4/B5 -> 63492.063
A7: Mean | B7: 0
A8: Daily | B8: 0.1
A9: Interval | B9: 0.1 | D9: Mismatch Δ(S−F) ($/bbl) | E9: Lower | F9: Upper | G9: Prob | H9: Expected P&L | I9: P&L
A10: G Total | B10: =SUM(G10:G50) -> 1 | D10: -2 | E10: =D10 - $B$9/2 -> -2.05 | F10: =D10 + $B$9/2 -> -1.95 | G10: =_xlfn.NORM.DIST(F10,$B$7,$B$8,TRUE)- _xlfn.NORM.DIST(E10,$B$7,$B$8,TRUE) -> 5.4891155e-85 | H10: =G10*D10*$B$6 -> -6.9703054e-80 | I10: =$B$6*D10 -> -126984.13
D11: -1.9 | E11: =D11 - $B$9/2 -> -1.95 | F11: =D11 + $B$9/2 -> -1.85 | G11: =_xlfn.NORM.DIST(F11,$B$7,$B$8,TRUE)- _xlfn.NORM.DIST(E11,$B$7,$B$8,TRUE) -> 1.0323699e-76 | H11: =G11*D11*$B$6 -> -1.2453986e-71 | I11: =$B$6*D11 -> -120634.92
D12: -1.8 | E12: =D12 - $B$9/2 -> -1.85 | F12: =D12 + $B$9/2 -> -1.75 | G12: =_xlfn.NORM.DIST(F12,$B$7,$B$8,TRUE)- _xlfn.NORM.DIST(E12,$B$7,$B$8,TRUE) -> 7.1634587e-69 | H12: =G12*D12*$B$6 -> -8.1868099e-64 | I12: =$B$6*D12 -> -114285.71
D13: -1.7 | E13: =D13 - $B$9/2 -> -1.75 | F13: =D13 + $B$9/2 -> -1.65 | G13: =_xlfn.NORM.DIST(F13,$B$7,$B$8,TRUE)- _xlfn.NORM.DIST(E13,$B$7,$B$8,TRUE) -> 1.8344629e-61 | H13: =G13*D13*$B$6 -> -1.9800552e-56 | I13: =$B$6*D13 -> -107936.51
D14: -1.6 | E14: =D14 - $B$9/2 -> -1.65 | F14: =D14 + $B$9/2 -> -1.55 | G14: =_xlfn.NORM.DIST(F14,$B$7,$B$8,TRUE)- _xlfn.NORM.DIST(E14,$B$7,$B$8,TRUE) -> 1.7344606e-54 | H14: =G14*D14*$B$6 -> -1.7619917e-49 | I14: =$B$6*D14 -> -101587.3
D15: -1.5 | E15: =D15 - $B$9/2 -> -1.55 | F15: =D15 + $B$9/2 -> -1.45 | G15: =_xlfn.NORM.DIST(F15,$B$7,$B$8,TRUE)- _xlfn.NORM.DIST(E15,$B$7,$B$8,TRUE) -> 6.057493e-48 | H15: =G15*D15*$B$6 -> -5.769041e-43 | I15: =$B$6*D15 -> -95238.095
D16: -1.4 | E16: =D16 - $B$9/2 -> -1.45 | F16: =D16 + $B$9/2 -> -1.35 | G16: =_xlfn.NORM.DIST(F16,$B$7,$B$8,TRUE)- _xlfn.NORM.DIST(E16,$B$7,$B$8,TRUE) -> 7.8188012e-42 | H16: =G16*D16*$B$6 -> -6.9500456e-37 | I16: =$B$6*D16 -> -88888.889
D17: -1.3 | E17: =D17 - $B$9/2 -> -1.35 | F17: =D17 + $B$9/2 -> -1.25 | G17: =_xlfn.NORM.DIST(F17,$B$7,$B$8,TRUE)- _xlfn.NORM.DIST(E17,$B$7,$B$8,TRUE) -> 3.7325565e-36 | H17: =G17*D17*$B$6 -> -3.0808403e-31 | I17: =$B$6*D17 -> -82539.683
D18: -1.2 | E18: =D18 - $B$9/2 -> -1.25 | F18: =D18 + $B$9/2 -> -1.15 | G18: =_xlfn.NORM.DIST(F18,$B$7,$B$8,TRUE)- _xlfn.NORM.DIST(E18,$B$7,$B$8,TRUE) -> 6.5957341e-31 | H18: =G18*D18*$B$6 -> -5.0253212e-26 | I18: =$B$6*D18 -> -76190.476
D19: -1.1 | E19: =D19 - $B$9/2 -> -1.15 | F19: =D19 + $B$9/2 -> -1.05 | G19: =_xlfn.NORM.DIST(F19,$B$7,$B$8,TRUE)- _xlfn.NORM.DIST(E19,$B$7,$B$8,TRUE) -> 4.3189404e-26 | H19: =G19*D19*$B$6 -> -3.0164028e-21 | I19: =$B$6*D19 -> -69841.27
D20: -1 | E20: =D20 - $B$9/2 -> -1.05 | F20: =D20 + $B$9/2 -> -0.95 | G20: =_xlfn.NORM.DIST(F20,$B$7,$B$8,TRUE)- _xlfn.NORM.DIST(E20,$B$7,$B$8,TRUE) -> 1.0494083e-21 | H20: =G20*D20*$B$6 -> -6.66291e-17 | I20: =$B$6*D20 -> -63492.063
D21: -0.9 | E21: =D21 - $B$9/2 -> -0.95 | F21: =D21 + $B$9/2 -> -0.85 | G21: =_xlfn.NORM.DIST(F21,$B$7,$B$8,TRUE)- _xlfn.NORM.DIST(E21,$B$7,$B$8,TRUE) -> 9.4784854e-18 | H21: =G21*D21*$B$6 -> -5.4162774e-13 | I21: =$B$6*D21 -> -57142.857
D22: -0.8 | E22: =D22 - $B$9/2 -> -0.85 | F22: =D22 + $B$9/2 -> -0.75 | G22: =_xlfn.NORM.DIST(F22,$B$7,$B$8,TRUE)- _xlfn.NORM.DIST(E22,$B$7,$B$8,TRUE) -> 3.1899437e-14 | H22: =G22*D22*$B$6 -> -1.6202889e-09 | I22: =$B$6*D22 -> -50793.651
... D50: 2 | E50: =D50 - $B$9/2 -> 1.95 | F50: =D50 + $B$9/2 -> 2.05 | G50: =_xlfn.NORM.DIST(F50,$B$7,$B$8,TRUE)- _xlfn.NORM.DIST(E50,$B$7,$B$8,TRUE) -> 0 | H50: =G50*D50*$B$6 -> 0 | I50: =$B$6*D50 -> 126984.13

Sheet Basis Risk
A1: Label | B1: Example
A2: Quantity | B2: 160000000
A3: Hedge Ratio | B3: 1
A4: Total Volume | B4: =B2*B3 -> 160000000
A5: N | B5: =10*12 -> 120
A6: Monthly Volume | B6: =B4/B5 -> 1333333.3
A7: Mean | B7: 0
A8: Monthly Sigma | B8: =0.1*SQRT(21) -> 0.45825757
A9: Interval | B9: 0.1 | D9: Mismatch Δ(S−F) ($/bbl) | E9: Lower | F9: Upper | G9: Prob | H9: Expected P&L | I9: P&L
D10: -2 | E10: =D10 - $B$9/2 -> -2.05 | F10: =D10 + $B$9/2 -> -1.95 | G10: =_xlfn.NORM.DIST(F10,$B$7,$B$8,TRUE)- _xlfn.NORM.DIST(E10,$B$7,$B$8,TRUE) -> 6.592755e-06 | H10: =G10*D10*$B$6 -> -17.58068 | I10: =$B$6*D10 -> -2666666.7
D11: -1.9 | E11: =D11 - $B$9/2 -> -1.95 | F11: =D11 + $B$9/2 -> -1.85 | G11: =_xlfn.NORM.DIST(F11,$B$7,$B$8,TRUE)- _xlfn.NORM.DIST(E11,$B$7,$B$8,TRUE) -> 1.6625131e-05 | H11: =G11*D11*$B$6 -> -42.116999 | I11: =$B$6*D11 -> -2533333.3
D12: -1.8 | E12: =D12 - $B$9/2 -> -1.85 | F12: =D12 + $B$9/2 -> -1.75 | G12: =_xlfn.NORM.DIST(F12,$B$7,$B$8,TRUE)- _xlfn.NORM.DIST(E12,$B$7,$B$8,TRUE) -> 3.9981698e-05 | H12: =G12*D12*$B$6 -> -95.956074 | I12: =$B$6*D12 -> -2400000
D13: -1.7 | E13: =D13 - $B$9/2 -> -1.75 | F13: =D13 + $B$9/2 -> -1.65 | G13: =_xlfn.NORM.DIST(F13,$B$7,$B$8,TRUE)- _xlfn.NORM.DIST(E13,$B$7,$B$8,TRUE) -> 9.1697123e-05 | H13: =G13*D13*$B$6 -> -207.84681 | I13: =$B$6*D13 -> -2266666.7
D14: -1.6 | E14: =D14 - $B$9/2 -> -1.65 | F14: =D14 + $B$9/2 -> -1.55 | G14: =_xlfn.NORM.DIST(F14,$B$7,$B$8,TRUE)- _xlfn.NORM.DIST(E14,$B$7,$B$8,TRUE) -> 0.00020056208 | H14: =G14*D14*$B$6 -> -427.86577 | I14: =$B$6*D14 -> -2133333.3
A15: G Total | B15: =SUM(G10:G50) -> 0.9999923 | D15: -1.5 | E15: =D15 - $B$9/2 -> -1.55 | F15: =D15 + $B$9/2 -> -1.45 | G15: =_xlfn.NORM.DIST(F15,$B$7,$B$8,TRUE)- _xlfn.NORM.DIST(E15,$B$7,$B$8,TRUE) -> 0.00041835105 | H15: =G15*D15*$B$6 -> -836.70211 | I15: =$B$6*D15 -> -2000000
D16: -1.4 | E16: =D16 - $B$9/2 -> -1.45 | F16: =D16 + $B$9/2 -> -1.35 | G16: =_xlfn.NORM.DIST(F16,$B$7,$B$8,TRUE)- _xlfn.NORM.DIST(E16,$B$7,$B$8,TRUE) -> 0.00083220843 | H16: =G16*D16*$B$6 -> -1553.4557 | I16: =$B$6*D16 -> -1866666.7
D17: -1.3 | E17: =D17 - $B$9/2 -> -1.35 | F17: =D17 + $B$9/2 -> -1.25 | G17: =_xlfn.NORM.DIST(F17,$B$7,$B$8,TRUE)- _xlfn.NORM.DIST(E17,$B$7,$B$8,TRUE) -> 0.0015787844 | H17: =G17*D17*$B$6 -> -2736.5596 | I17: =$B$6*D17 -> -1733333.3
D18: -1.2 | E18: =D18 - $B$9/2 -> -1.25 | F18: =D18 + $B$9/2 -> -1.15 | G18: =_xlfn.NORM.DIST(F18,$B$7,$B$8,TRUE)- _xlfn.NORM.DIST(E18,$B$7,$B$8,TRUE) -> 0.0028563619 | H18: =G18*D18*$B$6 -> -4570.179 | I18: =$B$6*D18 -> -1600000
D19: -1.1 | E19: =D19 - $B$9/2 -> -1.15 | F19: =D19 + $B$9/2 -> -1.05 | G19: =_xlfn.NORM.DIST(F19,$B$7,$B$8,TRUE)- _xlfn.NORM.DIST(E19,$B$7,$B$8,TRUE) -> 0.0049283729 | H19: =G19*D19*$B$6 -> -7228.2803 | I19: =$B$6*D19 -> -1466666.7
D20: -1 | E20: =D20 - $B$9/2 -> -1.05 | F20: =D20 + $B$9/2 -> -0.95 | G20: =_xlfn.NORM.DIST(F20,$B$7,$B$8,TRUE)- _xlfn.NORM.DIST(E20,$B$7,$B$8,TRUE) -> 0.0081094992 | H20: =G20*D20*$B$6 -> -10812.666 | I20: =$B$6*D20 -> -1333333.3
D21: -0.9 | E21: =D21 - $B$9/2 -> -0.95 | F21: =D21 + $B$9/2 -> -0.85 | G21: =_xlfn.NORM.DIST(F21,$B$7,$B$8,TRUE)- _xlfn.NORM.DIST(E21,$B$7,$B$8,TRUE) -> 0.012725792 | H21: =G21*D21*$B$6 -> -15270.951 | I21: =$B$6*D21 -> -1200000
D22: -0.8 | E22: =D22 - $B$9/2 -> -0.85 | F22: =D22 + $B$9/2 -> -0.75 | G22: =_xlfn.NORM.DIST(F22,$B$7,$B$8,TRUE)- _xlfn.NORM.DIST(E22,$B$7,$B$8,TRUE) -> 0.019044788 | H22: =G22*D22*$B$6 -> -20314.44 | I22: =$B$6*D22 -> -1066666.7
D23: -0.7 | E23: =D23 - $B$9/2 -> -0.75 | F23: =D23 + $B$9/2 -> -0.65 | G23: =_xlfn.NORM.DIST(F23,$B$7,$B$8,TRUE)- _xlfn.NORM.DIST(E23,$B$7,$B$8,TRUE) -> 0.027181167 | H23: =G23*D23*$B$6 -> -25369.089 | I23: =$B$6*D23 -> -933333.33
D24: -0.6 | E24: =D24 - $B$9/2 -> -0.65 | F24: =D24 + $B$9/2 -> -0.55 | G24: =_xlfn.NORM.DIST(F24,$B$7,$B$8,TRUE)- _xlfn.NORM.DIST(E24,$B$7,$B$8,TRUE) -> 0.036996517 | H24: =G24*D24*$B$6 -> -29597.214 | I24: =$B$6*D24 -> -800000
D25: -0.5 | E25: =D25 - $B$9/2 -> -0.55 | F25: =D25 + $B$9/2 -> -0.45 | G25: =_xlfn.NORM.DIST(F25,$B$7,$B$8,TRUE)- _xlfn.NORM.DIST(E25,$B$7,$B$8,TRUE) -> 0.048023577 | H25: =G25*D25*$B$6 -> -32015.718 | I25: =$B$6*D25 -> -666666.67
D26: -0.4 | E26: =D26 - $B$9/2 -> -0.45 | F26: =D26 + $B$9/2 -> -0.35 | G26: =_xlfn.NORM.DIST(F26,$B$7,$B$8,TRUE)- _xlfn.NORM.DIST(E26,$B$7,$B$8,TRUE) -> 0.059449633 | H26: =G26*D26*$B$6 -> -31706.471 | I26: =$B$6*D26 -> -533333.33
D27: -0.3 | E27: =D27 - $B$9/2 -> -0.35 | F27: =D27 + $B$9/2 -> -0.25 | G27: =_xlfn.NORM.DIST(F27,$B$7,$B$8,TRUE)- _xlfn.NORM.DIST(E27,$B$7,$B$8,TRUE) -> 0.070185105 | H27: =G27*D27*$B$6 -> -28074.042 | I27: =$B$6*D27 -> -400000
... D50: 2 | E50: =D50 - $B$9/2 -> 1.95 | F50: =D50 + $B$9/2 -> 2.05 | G50: =_xlfn.NORM.DIST(F50,$B$7,$B$8,TRUE)- _xlfn.NORM.DIST(E50,$B$7,$B$8,TRUE) -> 6.592755e-06 | H50: =G50*D50*$B$6 -> 17.58068 | I50: =$B$6*D50 -> 2666666.7

Sheet Liquidity Risk
A2: Monthly Volume | B2: =160000000/120 -> 1333333.3
A3: Hedge Ratio | B3: 1
A4: Contract Size (bbl) | B4: 1000
A5: Months Stacked (k) | B5: 12
A6: Daily Sigma | B6: =0.1 -> 0.1
A7: Horizon | B7: 21
A8: Starting Liquidity | B8: 1000000000
A9: Hedged Stack Volume | B9: =B5*B2 -> 16000000
A10: Futures Contracts | B10: =B9/B4 -> 16000
A11: Commercial Margin | B11: 4
A12: Collection Factor | B12: 0.98 | C12: Counter Party Risk
A14: Day | B14: ΔF ($/bbl) | C14: VM cash ($) | D14: Customer inflow ($) | E14: Net flow ($) | F14: Cash Balance | G14: Running Min.
A15: 1 | B15: -0.034311245 | C15: =$B$2*B15 -> -45748.327 | D15: =IF(A15=$B$7, $B$11 * $B$12*$B$2, 0) -> 0 | E15: =C15+D15 -> -45748.327 | F15: =B8+E15 -> 9.9995425e+08 | G15: =F15 -> 9.9995425e+08
A16: 2 | B16: -0.013696908 | C16: =$B$2*B16 -> -18262.544 | D16: =IF(A16=$B$7, $B$11 * $B$12*$B$2, 0) -> 0 | E16: =C16+D16 -> -18262.544 | F16: =F15+E16 -> 9.9993599e+08 | G16: =MIN(G15,F16) -> 9.9993599e+08
A17: 3 | B17: -0.0012569985 | C17: =$B$2*B17 -> -1675.9981 | D17: =IF(A17=$B$7, $B$11 * $B$12*$B$2, 0) -> 0 | E17: =C17+D17 -> -1675.9981 | F17: =F16+E17 -> 9.9993431e+08 | G17: =MIN(G16,F17) -> 9.9993431e+08
A18: 4 | B18: 0.12858583 | C18: =$B$2*B18 -> 171447.77 | D18: =IF(A18=$B$7, $B$11 * $B$12*$B$2, 0) -> 0 | E18: =C18+D18 -> 171447.77 | F18: =F17+E18 -> 1.0001058e+09 | G18: =MIN(G17,F18) -> 9.9993431e+08
A19: 5 | B19: -0.04930533 | C19: =$B$2*B19 -> -65740.44 | D19: =IF(A19=$B$7, $B$11 * $B$12*$B$2, 0) -> 0 | E19: =C19+D19 -> -65740.44 | F19: =F18+E19 -> 1.00004e+09 | G19: =MIN(G18,F19) -> 9.9993431e+08
A20: 6 | B20: 0.027704338 | C20: =$B$2*B20 -> 36939.118 | D20: =IF(A20=$B$7, $B$11 * $B$12*$B$2, 0) -> 0 | E20: =C20+D20 -> 36939.118 | F20: =F19+E20 -> 1.000077e+09 | G20: =MIN(G19,F20) -> 9.9993431e+08
A21: 7 | B21: 0.0026037983 | C21: =$B$2*B21 -> 3471.731 | D21: =IF(A21=$B$7, $B$11 * $B$12*$B$2, 0) -> 0 | E21: =C21+D21 -> 3471.731 | F21: =F20+E21 -> 1.0000804e+09 | G21: =MIN(G20,F21) -> 9.9993431e+08
A22: 8 | B22: -0.003725438 | C22: =$B$2*B22 -> -4967.2507 | D22: =IF(A22=$B$7, $B$11 * $B$12*$B$2, 0) -> 0 | E22: =C22+D22 -> -4967.2507 | F22: =F21+E22 -> 1.0000755e+09 | G22: =MIN(G21,F22) -> 9.9993431e+08
A23: 9 | B23: -0.11106865 | C23: =$B$2*B23 -> -148091.53 | D23: =IF(A23=$B$7, $B$11 * $B$12*$B$2, 0) -> 0 | E23: =C23+D23 -> -148091.53 | F23: =F22+E23 -> 9.9992737e+08 | G23: =MIN(G22,F23) -> 9.9992737e+08
A24: 10 | B24: 0.082663461 | C24: =$B$2*B24 -> 110217.95 | D24: =IF(A24=$B$7, $B$11 * $B$12*$B$2, 0) -> 0 | E24: =C24+D24 -> 110217.95 | F24: =F23+E24 -> 1.0000376e+09 | G24: =MIN(G23,F24) -> 9.9992737e+08
A25: 11 | B25: -0.091094051 | C25: =$B$2*B25 -> -121458.73 | D25: =IF(A25=$B$7, $B$11 * $B$12*$B$2, 0) -> 0 | E25: =C25+D25 -> -121458.73 | F25: =F24+E25 -> 9.9991613e+08 | G25: =MIN(G24,F25) -> 9.9991613e+08
A26: 12 | B26: -0.090062685 | C26: =$B$2*B26 -> -120083.58 | D26: =IF(A26=$B$7, $B$11 * $B$12*$B$2, 0) -> 0 | E26: =C26+D26 -> -120083.58 | F26: =F25+E26 -> 9.9979605e+08 | G26: =MIN(G25,F26) -> 9.9979605e+08
A27: 13 | B27: 0.0041527953 | C27: =$B$2*B27 -> 5537.0604 | D27: =IF(A27=$B$7, $B$11 * $B$12*$B$2, 0) -> 0 | E27: =C27+D27 -> 5537.0604 | F27: =F26+E27 -> 9.9980159e+08 | G27: =MIN(G26,F27) -> 9.9979605e+08
... A35: 21 | B35: -0.050182954 | C35: =$B$2*B35 -> -66910.605 | D35: =IF(A35=$B$7, $B$11 * $B$12*$B$2, 0) -> 5226666.7 | E35: =C35+D35 -> 5159756.1 | F35: =F34+E35 -> 1.0046351e+09 | G35: =MIN(G34,F35) -> 9.9947531e+08

Sheet Liquidity Squeeze Test
A1: Starting Liquid. | B1: 1000000000
A2: Daily Sigma | B2: 0.4
A3: Hedged Barrels | B3: =16000000 -> 16000000
A4: Trading Days | B4: 21
A5: Monthly Sigma | B5: =B2*SQRT(B4) -> 1.8330303
A6: Mean | B6: 0
B8: Monthly Change | C8: VM Cash | E8: Expected VM | F8: StdDev VM | G8: LAR 5% | I8: Day | J8: Daily LAR 5% | K8: Inflow | L8: Net Cash | M8: Liquidity Balance
B9: -3.7904223 | C9: =$B$3*B9 -> -60646757 | E9: =AVERAGE(C9:C21) -> 523203.38 | F9: =_xlfn.STDEV.S(C9:C21) -> 28296729 | G9: =_xlfn.PERCENTILE.INC(C9:C21,0.05) -> -53768522 | I9: 1 | J9: =$G$9/21 -> -2560405.8 | K9: 0 | L9: =K9+J9 -> -2560405.8 | M9: =B1+L9 -> 9.9743959e+08
B10: -3.0739395 | C10: =$B$3*B10 -> -49183032 | I10: 2 | J10: =$G$9/21 -> -2560405.8 | K10: 0 | L10: =K10+J10 -> -2560405.8 | M10: =M9+L10 -> 9.9487919e+08
B11: 0.95139286 | C11: =$B$3*B11 -> 15222286 | G11: Hypothetical Spot at LAR 5% | I11: 3 | J11: =$G$9/21 -> -2560405.8 | K11: 0 | L11: =K11+J11 -> -2560405.8 | M11: =M10+L11 -> 9.9231878e+08
B12: 1.8683837 | C12: =$B$3*B12 -> 29894140 | G12: 75 | I12: 4 | J12: =$G$9/21 -> -2560405.8 | K12: 0 | L12: =K12+J12 -> -2560405.8 | M12: =M11+L12 -> 9.8975838e+08
B13: -0.048902701 | C13: =$B$3*B13 -> -782443.21 | I13: 5 | J13: =$G$9/21 -> -2560405.8 | K13: 0 | L13: =K13+J13 -> -2560405.8 | M13: =M12+L13 -> 9.8719797e+08
B14: -0.4066411 | C14: =$B$3*B14 -> -6506257.5 | I14: 6 | J14: =$G$9/21 -> -2560405.8 | K14: 0 | L14: =K14+J14 -> -2560405.8 | M14: =M13+L14 -> 9.8463757e+08
B15: 1.2321719 | C15: =$B$3*B15 -> 19714751 | I15: 7 | J15: =$G$9/21 -> -2560405.8 | K15: 0 | L15: =K15+J15 -> -2560405.8 | M15: =M14+L15 -> 9.8207716e+08
B16: 1.8937106 | C16: =$B$3*B16 -> 30299370 | I16: 8 | J16: =$G$9/21 -> -2560405.8 | K16: 0 | L16: =K16+J16 -> -2560405.8 | M16: =M15+L16 -> 9.7951675e+08
B17: -0.84733709 | C17: =$B$3*B17 -> -13557393 | I17: 9 | J17: =$G$9/21 -> -2560405.8 | K17: 0 | L17: =K17+J17 -> -2560405.8 | M17: =M16+L17 -> 9.7695635e+08
B18: 1.5741529 | C18: =$B$3*B18 -> 25186446 | I18: 10 | J18: =$G$9/21 -> -2560405.8 | K18: 0 | L18: =K18+J18 -> -2560405.8 | M18: =M17+L18 -> 9.7439594e+08
B19: 0.89400758 | C19: =$B$3*B19 -> 14304121 | I19: 11 | J19: =$G$9/21 -> -2560405.8 | K19: 0 | L19: =K19+J19 -> -2560405.8 | M19: =M18+L19 -> 9.7183554e+08
B20: -0.070850753 | C20: =$B$3*B20 -> -1133612 | I20: 12 | J20: =$G$9/21 -> -2560405.8 | K20: 0 | L20: =K20+J20 -> -2560405.8 | M20: =M19+L20 -> 9.6927513e+08
B21: 0.24937663 | C21: =$B$3*B21 -> 3990026 | I21: 13 | J21: =$G$9/21 -> -2560405.8 | K21: 0 | L21: =K21+J21 -> -2560405.8 | M21: =M20+L21 -> 9.6671472e+08
I22: 14 | J22: =$G$9/21 -> -2560405.8 | K22: 0 | L22: =K22+J22 -> -2560405.8 | M22: =M21+L22 -> 9.6415432e+08
I23: 15 | J23: =$G$9/21 -> -2560405.8 | K23: 0 | L23: =K23+J23 -> -2560405.8 | M23: =M22+L23 -> 9.6159391e+08
I24: 16 | J24: =$G$9/21 -> -2560405.8 | K24: 0 | L24: =K24+J24 -> -2560405.8 | M24: =M23+L24 -> 9.5903351e+08
I25: 17 | J25: =$G$9/21 -> -2560405.8 | K25: 0 | L25: =K25+J25 -> -2560405.8 | M25: =M24+L25 -> 9.564731e+08
I26: 18 | J26: =$G$9/21 -> -2560405.8 | K26: 0 | L26: =K26+J26 -> -2560405.8 | M26: =M25+L26 -> 9.539127e+08
I27: 19 | J27: =$G$9/21 -> -2560405.8 | K27: 0 | L27: =K27+J27 -> -2560405.8 | M27: =M26+L27 -> 9.5135229e+08
I28: 20 | J28: =$G$9/21 -> -2560405.8 | K28: 0 | L28: =K28+J28 -> -2560405.8 | M28: =M27+L28 -> 9.4879188e+08
I29: 21 | J29: =($G$9/21) -> -2560405.8 | L29: =K29+J29 -> -2560405.8 | M29: =M28+L29 -> 9.4623148e+08

Sheet Testing Button
B3: Adjust the Calculations of the Following sheets by changing the futures price, be reasonable with the number Spot Price is about 80
B5: Futures Price | C5: 76

Sheet Loss At Risk Analysis
A3: Basis Ratio | B3: ='Testing Button'!C5/80 -> 0.95
A4: Lower Bound | B4: {=_xlfn.IFS(B3<1,0.01,B3<1.05,0.1,TRUE,0.22)} -> 0.01 | E4: Basis Range | F4: Sigma Range
A5: Upper Bound | B5: {=_xlfn.IFS(B3<1,0.1,B3<1.05,0.22,TRUE,0.4)} -> 0.1 | E5: <0.9875 | F5: .01-.1
A6: Random Sigma | B6: =B4+(B5-B4)*RAND() -> 0.083147684 | E6: 1–1.05 | F6: 0.1-0.22
A7: Hedged Barrels | B7: =16000000 -> 16000000 | E7: >=1.05 | F7: .22-.4
A8: Monthly SD | B8: =B6*SQRT(11) -> 0.27576967
A9: Mean | B9: 0
A11: Monthly Change | B11: CashFlow | D11: Expected CF | E11: Standard Deviation | F11: LAR 5%
A12: =_xlfn.NORM.INV(RAND(),$B$9,$B$8) -> -0.1309853 | B12: =$B$7*A12 -> -2095764.7 | D12: =AVERAGE(B12:B23) -> -1089357.1 | E12: =_xlfn.STDEV.S(B12:B23) -> 3944549 | F12: =_xlfn.PERCENTILE.INC(B12:B23,0.05) -> -5990037.1
A13: =_xlfn.NORM.INV(RAND(),$B$9,$B$8) -> -0.41002725 | B13: =$B$7*A13 -> -6560436
A14: =_xlfn.NORM.INV(RAND(),$B$9,$B$8) -> 0.22238501 | B14: =$B$7*A14 -> 3558160.1
A15: =_xlfn.NORM.INV(RAND(),$B$9,$B$8) -> -0.23187187 | B15: =$B$7*A15 -> -3709949.9
A16: =_xlfn.NORM.INV(RAND(),$B$9,$B$8) -> -0.34520919 | B16: =$B$7*A16 -> -5523347.1
A17: =_xlfn.NORM.INV(RAND(),$B$9,$B$8) -> -0.27842948 | B17: =$B$7*A17 -> -4454871.6
A18: =_xlfn.NORM.INV(RAND(),$B$9,$B$8) -> 0.36070214 | B18: =$B$7*A18 -> 5771234.2
A19: =_xlfn.NORM.INV(RAND(),$B$9,$B$8) -> -0.1469517 | B19: =$B$7*A19 -> -2351227.3
A20: =_xlfn.NORM.INV(RAND(),$B$9,$B$8) -> 0.17399787 | B20: =$B$7*A20 -> 2783965.9
A21: =_xlfn.NORM.INV(RAND(),$B$9,$B$8) -> -0.10888106 | B21: =$B$7*A21 -> -1742097
A22: =_xlfn.NORM.INV(RAND(),$B$9,$B$8) -> -0.10598189 | B22: =$B$7*A22 -> -1695710.2
A23: =_xlfn.NORM.INV(RAND(),$B$9,$B$8) -> 0.18423488 | B23: =$B$7*A23 -> 2947758.1

Sheet StacknRoll Strategy Analysis
A2: Spot | B2: 80
A3: Next Futures | B3: ='Testing Button'!C5 -> 76
A4: Monthly Return | B4: =(B3-B2)/B3 -> -0.052631579
A5: Backwardation | B5: ='Testing Button'!C6 -> 0
A6: Volatility | B6: ='Loss At Risk Analysis'!B8 -> 0.27576967
A7: Horizon | B7: 12
A8: Monthly Volume | B8: =160000000/120 -> 1333333.3
A9: Fixed Price (bbl) | B9: 80
A12: Month | B12: Front Price | C12: Next-Month | D12: Roll P&L | E12: Total Roll P&L | F12: Delivery P&L | G12: Total Delivery P&L
A13: 1 | B13: =_xlfn.NORM.INV(RAND(),$B$9,$B$6) -> 79.498523 | C13: =B13*(1+$B$4) -> 75.31439 | D13: =B13-C13 -> 4.1841328 | E13: =D13*$B$8 -> 5578843.7 | F13: =C13-$B$9 -> -4.6856095 | G13: =F13*$B$8 -> -6247479.4
A14: 2 | B14: =_xlfn.NORM.INV(RAND(),$B$9,$B$6) -> 79.88173 | C14: =B14*(1+$B$4) -> 75.677428 | D14: =B14-C14 -> 4.2043016 | E14: =D14*$B$8 -> 5605735.4 | F14: =C14-$B$9 -> -4.3225716 | G14: =F14*$B$8 -> -5763428.9
A15: 3 | B15: =_xlfn.NORM.INV(RAND(),$B$9,$B$6) -> 80.131768 | C15: =B15*(1+$B$4) -> 75.914306 | D15: =B15-C15 -> 4.2174615 | E15: =D15*$B$8 -> 5623282 | F15: =C15-$B$9 -> -4.0856936 | G15: =F15*$B$8 -> -5447591.5
A16: 4 | B16: =_xlfn.NORM.INV(RAND(),$B$9,$B$6) -> 79.97507 | C16: =B16*(1+$B$4) -> 75.765856 | D16: =B16-C16 -> 4.2092142 | E16: =D16*$B$8 -> 5612285.6 | F16: =C16-$B$9 -> -4.2341443 | G16: =F16*$B$8 -> -5645525.7
A17: 5 | B17: =_xlfn.NORM.INV(RAND(),$B$9,$B$6) -> 80.068827 | C17: =B17*(1+$B$4) -> 75.854678 | D17: =B17-C17 -> 4.2141488 | E17: =D17*$B$8 -> 5618865 | F17: =C17-$B$9 -> -4.1453221 | G17: =F17*$B$8 -> -5527096.1
A18: 6 | B18: =_xlfn.NORM.INV(RAND(),$B$9,$B$6) -> 79.879877 | C18: =B18*(1+$B$4) -> 75.675673 | D18: =B18-C18 -> 4.2042041 | E18: =D18*$B$8 -> 5605605.4 | F18: =C18-$B$9 -> -4.3243267 | G18: =F18*$B$8 -> -5765768.9
A19: 7 | B19: =_xlfn.NORM.INV(RAND(),$B$9,$B$6) -> 79.8244 | C19: =B19*(1+$B$4) -> 75.623116 | D19: =B19-C19 -> 4.2012842 | E19: =D19*$B$8 -> 5601712.3 | F19: =C19-$B$9 -> -4.376884 | G19: =F19*$B$8 -> -5835845.3
A20: 8 | B20: =_xlfn.NORM.INV(RAND(),$B$9,$B$6) -> 80.530519 | C20: =B20*(1+$B$4) -> 76.29207 | D20: =B20-C20 -> 4.2384483 | E20: =D20*$B$8 -> 5651264.5 | F20: =C20-$B$9 -> -3.7079297 | G20: =F20*$B$8 -> -4943906.3
A21: 9 | B21: =_xlfn.NORM.INV(RAND(),$B$9,$B$6) -> 79.575315 | C21: =B21*(1+$B$4) -> 75.38714 | D21: =B21-C21 -> 4.1881745 | E21: =D21*$B$8 -> 5584232.6 | F21: =C21-$B$9 -> -4.6128595 | G21: =F21*$B$8 -> -6150479.4
A22: 10 | B22: =_xlfn.NORM.INV(RAND(),$B$9,$B$6) -> 80.009576 | C22: =B22*(1+$B$4) -> 75.798546 | D22: =B22-C22 -> 4.2110303 | E22: =D22*$B$8 -> 5614707.1 | F22: =C22-$B$9 -> -4.2014543 | G22: =F22*$B$8 -> -5601939
A23: 11 | B23: =_xlfn.NORM.INV(RAND(),$B$9,$B$6) -> 80.211509 | C23: =B23*(1+$B$4) -> 75.989851 | D23: =B23-C23 -> 4.2216584 | E23: =D23*$B$8 -> 5628877.9 | F23: =C23-$B$9 -> -4.010149 | G23: =F23*$B$8 -> -5346865.3
A24: 12 | B24: =_xlfn.NORM.INV(RAND(),$B$9,$B$6) -> 79.972746 | C24: =B24*(1+$B$4) -> 75.763654 | D24: =B24-C24 -> 4.2090919 | E24: =D24*$B$8 -> 5612122.5 | F24: =C24-$B$9 -> -4.2363456 | G24: =F24*$B$8 -> -5648460.8
A25: Year | E25: =SUM(E13:E24) -> 67337534 | G25: =SUM(G13:G24) -> -67924387
G28: Net Total P&L | H28: =E25+G25 -> -586852.44

Sheet Hedge Ratio Analysis
A2: Backwardation Spread | B2: =AVERAGE('StacknRoll Strategy Analysis'!D13:D24) -> 4.2085959
A3: Monthly Volume | B3: =160000000/120 -> 1333333.3
A4: Months Stacked | B4: 12
A5: Horizon | B5: 12
A6: LAR | B6: ='Loss At Risk Analysis'!F12 -> -5990037.1
A7: Available Liquidity | B7: =1000000000/120 -> 8333333.3
A8: Funding Rate (annual) | B8: 0.08
A9: Hedge Ratio Grid Step | B9: 0.05
A10: Monthly Volume | B10: =1333333 -> 1333333
A11: Monthly Funding Rate | B11: =B8/12 -> 0.0066666667 | E11: Margin Call uses available liquidity for the month to simplify, $1bil/120 months
A14: H | B14: RollProfit($) | C14: LaR_h($) | D14: Delivery | E14: ShortFall/(Margin Call) | F14: FundingCost($) | G14: NetProfit($)
A15: 0 | B15: =A15*$B$2*$B$10*$B$5 -> 0 | C15: =A15*$B$6 -> 0 | D15: =B15*$B$6 -> 0 | E15: =MAX(0,(-C15+-B15)-$B$7) -> 0 | F15: =E15*$B$11*$B$5 -> 0 | G15: =B15-F15 -> 0
A16: =A15+$B$9 -> 0.05 | B16: =A16*$B$2*$B$10 -> 280572.99 | C16: =A16*$B$6 -> -299501.86 | D16: =$D$3*$B$10*A16 -> 0 | E16: =MAX(0,(-C16+-B16)-$B$7) -> 0 | F16: =E16*$B$11*$B$5 -> 0 | G16: =B16-F16+C16+D16 -> -18928.868
A17: =A16+$B$9 -> 0.1 | B17: =A17*$B$2*$B$10 -> 561145.98 | C17: =A17*$B$6 -> -599003.71 | D17: =$D$3*$B$10*A17 -> 0 | E17: =MAX(0,(-C17+-B17)-$B$7) -> 0 | F17: =E17*$B$11*$B$5 -> 0 | G17: =B17-F17+C17+D17 -> -37857.736
A18: =A17+$B$9 -> 0.15 | B18: =A18*$B$2*$B$10 -> 841718.97 | C18: =A18*$B$6 -> -898505.57 | D18: =$D$3*$B$10*A18 -> 0 | E18: =MAX(0,(-C18+-B18)-$B$7) -> 0 | F18: =E18*$B$11*$B$5 -> 0 | G18: =B18-F18+C18+D18 -> -56786.603
A19: =A18+$B$9 -> 0.2 | B19: =A19*$B$2*$B$10 -> 1122292 | C19: =A19*$B$6 -> -1198007.4 | D19: =$D$3*$B$10*A19 -> 0 | E19: =MAX(0,(-C19+-B19)-$B$7) -> 0 | F19: =E19*$B$11*$B$5 -> 0 | G19: =B19-F19+C19+D19 -> -75715.471
A20: =A19+$B$9 -> 0.25 | B20: =A20*$B$2*$B$10 -> 1402864.9 | C20: =A20*$B$6 -> -1497509.3 | D20: =$D$3*$B$10*A20 -> 0 | E20: =MAX(0,(-C20+-B20)-$B$7) -> 0 | F20: =E20*$B$11*$B$5 -> 0 | G20: =B20-F20+C20+D20 -> -94644.339
A21: =A20+$B$9 -> 0.3 | B21: =A21*$B$2*$B$10 -> 1683437.9 | C21: =A21*$B$6 -> -1797011.1 | D21: =$D$3*$B$10*A21 -> 0 | E21: =MAX(0,(-C21+-B21)-$B$7) -> 0 | F21: =E21*$B$11*$B$5 -> 0 | G21: =B21-F21+C21+D21 -> -113573.21
A22: =A21+$B$9 -> 0.35 | B22: =A22*$B$2*$B$10 -> 1964010.9 | C22: =A22*$B$6 -> -2096513 | D22: =$D$3*$B$10*A22 -> 0 | E22: =MAX(0,(-C22+-B22)-$B$7) -> 0 | F22: =E22*$B$11*$B$5 -> 0 | G22: =B22-F22+C22+D22 -> -132502.07
A23: =A22+$B$9 -> 0.4 | B23: =A23*$B$2*$B$10 -> 2244583.9 | C23: =A23*$B$6 -> -2396014.9 | D23: =$D$3*$B$10*A23 -> 0 | E23: =MAX(0,(-C23+-B23)-$B$7) -> 0 | F23: =E23*$B$11*$B$5 -> 0 | G23: =B23-F23+C23+D23 -> -151430.94
A24: =A23+$B$9 -> 0.45 | B24: =A24*$B$2*$B$10 -> 2525156.9 | C24: =A24*$B$6 -> -2695516.7 | D24: =$D$3*$B$10*A24 -> 0 | E24: =MAX(0,(-C24+-B24)-$B$7) -> 0 | F24: =E24*$B$11*$B$5 -> 0 | G24: =B24-F24+C24+D24 -> -170359.81
A25: =A24+$B$9 -> 0.5 | B25: =A25*$B$2*$B$10 -> 2805729.9 | C25: =A25*$B$6 -> -2995018.6 | D25: =$D$3*$B$10*A25 -> 0 | E25: =MAX(0,(-C25+-B25)-$B$7) -> 0 | F25: =E25*$B$11*$B$5 -> 0 | G25: =B25-F25+C25+D25 -> -189288.68
A26: =A25+$B$9 -> 0.55 | B26: =A26*$B$2*$B$10 -> 3086302.9 | C26: =A26*$B$6 -> -3294520.4 | D26: =$D$3*$B$10*A26 -> 0 | E26: =MAX(0,(-C26+-B26)-$B$7) -> 0 | F26: =E26*$B$11*$B$5 -> 0 | G26: =B26-F26+C26+D26 -> -208217.55
A27: =A26+$B$9 -> 0.6 | B27: =A27*$B$2*$B$10 -> 3366875.9 | C27: =A27*$B$6 -> -3594022.3 | D27: =$D$3*$B$10*A27 -> 0 | E27: =MAX(0,(-C27+-B27)-$B$7) -> 0 | F27: =E27*$B$11*$B$5 -> 0 | G27: =B27-F27+C27+D27 -> -227146.41
... A35: =A34+$B$9 -> 1 | B35: =A35*$B$2*$B$10 -> 5611459.8 | C35: =A35*$B$6 -> -5990037.1 | D35: =$D$3*$B$10*A35 -> 0 | E35: =MAX(0,(-C35+-B35)-$B$7) -> 0 | F35: =E35*$B$11*$B$5 -> 0 | G35: =B35-F35+C35+D35 -> -378577.36

Sheet Sensitivity Table
E6: Volume | F6: 1333333.3
C14: Backwardation | M14: Spot | N14: Contango
B15: H/Fnext | C15: 75 | D15: 75.5 | E15: 76 | F15: 76.5 | G15: 77 | H15: 77.5 | I15: 78 | J15: 78.5 | K15: 79 | L15: 79.5 | M15: 80 | N15: 80.5 | O15: 81 | P15: 81.5 | Q15: 82 | R15: 82.5 | S15: 83 | T15: 83.5 | U15: 84 | V15: 84.5 | W15: 85
B16: 0.05 | C16: =('StacknRoll Strategy Analysis'!$B$2-'Sensitivity Table'!C15)*$F$6+('Hedge Ratio Analysis'!$G$16-'Hedge Ratio Analysis'!$E$16) -> 6647737.8 | D16: =('StacknRoll Strategy Analysis'!$B$2-'Sensitivity Table'!D15)*$F$6+('Hedge Ratio Analysis'!$G$16-'Hedge Ratio Analysis'!$E$16) -> 5981071.1 | E16: =('StacknRoll Strategy Analysis'!$B$2-'Sensitivity Table'!E15)*$F$6+('Hedge Ratio Analysis'!$G$16-'Hedge Ratio Analysis'!$E$16) -> 5314404.5 | F16: =('StacknRoll Strategy Analysis'!$B$2-'Sensitivity Table'!F15)*$F$6+('Hedge Ratio Analysis'!$G$16-'Hedge Ratio Analysis'!$E$16) -> 4647737.8 | G16: =('StacknRoll Strategy Analysis'!$B$2-'Sensitivity Table'!G15)*$F$6+('Hedge Ratio Analysis'!$G$16-'Hedge Ratio Analysis'!$E$16) -> 3981071.1 | H16: =('StacknRoll Strategy Analysis'!$B$2-'Sensitivity Table'!H15)*$F$6+('Hedge Ratio Analysis'!$G$16-'Hedge Ratio Analysis'!$E$16) -> 3314404.5 | I16: =('StacknRoll Strategy Analysis'!$B$2-'Sensitivity Table'!I15)*$F$6+('Hedge Ratio Analysis'!$G$16-'Hedge Ratio Analysis'!$E$16) -> 2647737.8 | J16: =('StacknRoll Strategy Analysis'!$B$2-'Sensitivity Table'!J15)*$F$6+('Hedge Ratio Analysis'!$G$16-'Hedge Ratio Analysis'!$E$16) -> 1981071.1 | ... W16: =('StacknRoll Strategy Analysis'!$B$2-'Sensitivity Table'!W15)*$F$6+('Hedge Ratio Analysis'!$G$16-'Hedge Ratio Analysis'!$E$16) -> -6685595.5
B17: 0.1 | C17: =('StacknRoll Strategy Analysis'!$B$2-'Sensitivity Table'!C15)*$F$6+('Hedge Ratio Analysis'!$G$17-'Hedge Ratio Analysis'!$E$17) -> 6628808.9 | D17: =('StacknRoll Strategy Analysis'!$B$2-'Sensitivity Table'!D15)*$F$6+('Hedge Ratio Analysis'!$G$17-'Hedge Ratio Analysis'!$E$17) -> 5962142.2 | E17: =('StacknRoll Strategy Analysis'!$B$2-'Sensitivity Table'!E15)*$F$6+('Hedge Ratio Analysis'!$G$17-'Hedge Ratio Analysis'!$E$17) -> 5295475.6 | F17: =('StacknRoll Strategy Analysis'!$B$2-'Sensitivity Table'!F15)*$F$6+('Hedge Ratio Analysis'!$G$17-'Hedge Ratio Analysis'!$E$17) -> 4628808.9 | G17: =('StacknRoll Strategy Analysis'!$B$2-'Sensitivity Table'!G15)*$F$6+('Hedge Ratio Analysis'!$G$17-'Hedge Ratio Analysis'!$E$17) -> 3962142.3 | H17: =('StacknRoll Strategy Analysis'!$B$2-'Sensitivity Table'!H15)*$F$6+('Hedge Ratio Analysis'!$G$17-'Hedge Ratio Analysis'!$E$17) -> 3295475.6 | I17: =('StacknRoll Strategy Analysis'!$B$2-'Sensitivity Table'!I15)*$F$6+('Hedge Ratio Analysis'!$G$17-'Hedge Ratio Analysis'!$E$17) -> 2628808.9 | J17: =('StacknRoll Strategy Analysis'!$B$2-'Sensitivity Table'!J15)*$F$6+('Hedge Ratio Analysis'!$G$17-'Hedge Ratio Analysis'!$E$17) -> 1962142.3 | ... W17: =('StacknRoll Strategy Analysis'!$B$2-'Sensitivity Table'!W15)*$F$6+('Hedge Ratio Analysis'!$G$17-'Hedge Ratio Analysis'!$E$17) -> -6704524.4
B18: 0.15 | C18: =('StacknRoll Strategy Analysis'!$B$2-'Sensitivity Table'!C15)*$F$6+('Hedge Ratio Analysis'!$G$18-'Hedge Ratio Analysis'!$E$18) -> 6609880 | D18: =('StacknRoll Strategy Analysis'!$B$2-'Sensitivity Table'!D15)*$F$6+('Hedge Ratio Analysis'!$G$18-'Hedge Ratio Analysis'!$E$18) -> 5943213.4 | E18: =('StacknRoll Strategy Analysis'!$B$2-'Sensitivity Table'!E15)*$F$6+('Hedge Ratio Analysis'!$G$18-'Hedge Ratio Analysis'!$E$18) -> 5276546.7 | F18: =('StacknRoll Strategy Analysis'!$B$2-'Sensitivity Table'!F15)*$F$6+('Hedge Ratio Analysis'!$G$18-'Hedge Ratio Analysis'!$E$18) -> 4609880.1 | G18: =('StacknRoll Strategy Analysis'!$B$2-'Sensitivity Table'!G15)*$F$6+('Hedge Ratio Analysis'!$G$18-'Hedge Ratio Analysis'!$E$18) -> 3943213.4 | H18: =('StacknRoll Strategy Analysis'!$B$2-'Sensitivity Table'!H15)*$F$6+('Hedge Ratio Analysis'!$G$18-'Hedge Ratio Analysis'!$E$18) -> 3276546.7 | I18: =('StacknRoll Strategy Analysis'!$B$2-'Sensitivity Table'!I15)*$F$6+('Hedge Ratio Analysis'!$G$18-'Hedge Ratio Analysis'!$E$18) -> 2609880.1 | J18: =('StacknRoll Strategy Analysis'!$B$2-'Sensitivity Table'!J15)*$F$6+('Hedge Ratio Analysis'!$G$18-'Hedge Ratio Analysis'!$E$18) -> 1943213.4 | ... W18: =('StacknRoll Strategy Analysis'!$B$2-'Sensitivity Table'!W15)*$F$6+('Hedge Ratio Analysis'!$G$18-'Hedge Ratio Analysis'!$E$18) -> -6723453.3
B19: 0.2 | C19: =('StacknRoll Strategy Analysis'!$B$2-'Sensitivity Table'!C15)*$F$6+('Hedge Ratio Analysis'!$G$19-'Hedge Ratio Analysis'!$E$19) -> 6590951.2 | D19: =('StacknRoll Strategy Analysis'!$B$2-'Sensitivity Table'!D15)*$F$6+('Hedge Ratio Analysis'!$G$19-'Hedge Ratio Analysis'!$E$19) -> 5924284.5 | E19: =('StacknRoll Strategy Analysis'!$B$2-'Sensitivity Table'!E15)*$F$6+('Hedge Ratio Analysis'!$G$19-'Hedge Ratio Analysis'!$E$19) -> 5257617.8 | F19: =('StacknRoll Strategy Analysis'!$B$2-'Sensitivity Table'!F15)*$F$6+('Hedge Ratio Analysis'!$G$19-'Hedge Ratio Analysis'!$E$19) -> 4590951.2 | G19: =('StacknRoll Strategy Analysis'!$B$2-'Sensitivity Table'!G15)*$F$6+('Hedge Ratio Analysis'!$G$19-'Hedge Ratio Analysis'!$E$19) -> 3924284.5 | H19: =('StacknRoll Strategy Analysis'!$B$2-'Sensitivity Table'!H15)*$F$6+('Hedge Ratio Analysis'!$G$19-'Hedge Ratio Analysis'!$E$19) -> 3257617.9 | I19: =('StacknRoll Strategy Analysis'!$B$2-'Sensitivity Table'!I15)*$F$6+('Hedge Ratio Analysis'!$G$19-'Hedge Ratio Analysis'!$E$19) -> 2590951.2 | J19: =('StacknRoll Strategy Analysis'!$B$2-'Sensitivity Table'!J15)*$F$6+('Hedge Ratio Analysis'!$G$19-'Hedge Ratio Analysis'!$E$19) -> 1924284.5 | ... W19: =('StacknRoll Strategy Analysis'!$B$2-'Sensitivity Table'!W15)*$F$6+('Hedge Ratio Analysis'!$G$19-'Hedge Ratio Analysis'!$E$19) -> -6742382.1
B20: 0.25 | C20: =('StacknRoll Strategy Analysis'!$B$2-'Sensitivity Table'!C15)*$F$6+('Hedge Ratio Analysis'!$G$20-'Hedge Ratio Analysis'!$E$20) -> 6572022.3 | D20: =('StacknRoll Strategy Analysis'!$B$2-'Sensitivity Table'!D15)*$F$6+('Hedge Ratio Analysis'!$G$20-'Hedge Ratio Analysis'!$E$20) -> 5905355.6 | E20: =('StacknRoll Strategy Analysis'!$B$2-'Sensitivity Table'!E15)*$F$6+('Hedge Ratio Analysis'!$G$20-'Hedge Ratio Analysis'!$E$20) -> 5238689 | F20: =('StacknRoll Strategy Analysis'!$B$2-'Sensitivity Table'!F15)*$F$6+('Hedge Ratio Analysis'!$G$20-'Hedge Ratio Analysis'!$E$20) -> 4572022.3 | G20: =('StacknRoll Strategy Analysis'!$B$2-'Sensitivity Table'!G15)*$F$6+('Hedge Ratio Analysis'!$G$20-'Hedge Ratio Analysis'!$E$20) -> 3905355.7 | H20: =('StacknRoll Strategy Analysis'!$B$2-'Sensitivity Table'!H15)*$F$6+('Hedge Ratio Analysis'!$G$20-'Hedge Ratio Analysis'!$E$20) -> 3238689 | I20: =('StacknRoll Strategy Analysis'!$B$2-'Sensitivity Table'!I15)*$F$6+('Hedge Ratio Analysis'!$G$20-'Hedge Ratio Analysis'!$E$20) -> 2572022.3 | J20: =('StacknRoll Strategy Analysis'!$B$2-'Sensitivity Table'!J15)*$F$6+('Hedge Ratio Analysis'!$G$20-'Hedge Ratio Analysis'!$E$20) -> 1905355.7 | ... W20: =('StacknRoll Strategy Analysis'!$B$2-'Sensitivity Table'!W15)*$F$6+('Hedge Ratio Analysis'!$G$20-'Hedge Ratio Analysis'!$E$20) -> -6761311
B21: 0.3 | C21: =('StacknRoll Strategy Analysis'!$B$2-'Sensitivity Table'!C15)*$F$6+('Hedge Ratio Analysis'!$G$21-'Hedge Ratio Analysis'!$E$21) -> 6553093.4 | D21: =('StacknRoll Strategy Analysis'!$B$2-'Sensitivity Table'!D15)*$F$6+('Hedge Ratio Analysis'!$G$21-'Hedge Ratio Analysis'!$E$21) -> 5886426.8 | E21: =('StacknRoll Strategy Analysis'!$B$2-'Sensitivity Table'!E15)*$F$6+('Hedge Ratio Analysis'!$G$21-'Hedge Ratio Analysis'!$E$21) -> 5219760.1 | F21: =('StacknRoll Strategy Analysis'!$B$2-'Sensitivity Table'!F15)*$F$6+('Hedge Ratio Analysis'!$G$21-'Hedge Ratio Analysis'!$E$21) -> 4553093.4 | G21: =('StacknRoll Strategy Analysis'!$B$2-'Sensitivity Table'!G15)*$F$6+('Hedge Ratio Analysis'!$G$21-'Hedge Ratio Analysis'!$E$21) -> 3886426.8 | H21: =('StacknRoll Strategy Analysis'!$B$2-'Sensitivity Table'!H15)*$F$6+('Hedge Ratio Analysis'!$G$21-'Hedge Ratio Analysis'!$E$21) -> 3219760.1 | I21: =('StacknRoll Strategy Analysis'!$B$2-'Sensitivity Table'!I15)*$F$6+('Hedge Ratio Analysis'!$G$21-'Hedge Ratio Analysis'!$E$21) -> 2553093.5 | J21: =('StacknRoll Strategy Analysis'!$B$2-'Sensitivity Table'!J15)*$F$6+('Hedge Ratio Analysis'!$G$21-'Hedge Ratio Analysis'!$E$21) -> 1886426.8 | ... W21: =('StacknRoll Strategy Analysis'!$B$2-'Sensitivity Table'!W15)*$F$6+('Hedge Ratio Analysis'!$G$21-'Hedge Ratio Analysis'!$E$21) -> -6780239.9
B22: 0.35 | C22: =('StacknRoll Strategy Analysis'!$B$2-'Sensitivity Table'!C15)*$F$6+('Hedge Ratio Analysis'!$G$22-'Hedge Ratio Analysis'!$E$22) -> 6534164.6 | D22: =('StacknRoll Strategy Analysis'!$B$2-'Sensitivity Table'!D15)*$F$6+('Hedge Ratio Analysis'!$G$22-'Hedge Ratio Analysis'!$E$22) -> 5867497.9 | E22: =('StacknRoll Strategy Analysis'!$B$2-'Sensitivity Table'!E15)*$F$6+('Hedge Ratio Analysis'!$G$22-'Hedge Ratio Analysis'!$E$22) -> 5200831.2 | F22: =('StacknRoll Strategy Analysis'!$B$2-'Sensitivity Table'!F15)*$F$6+('Hedge Ratio Analysis'!$G$22-'Hedge Ratio Analysis'!$E$22) -> 4534164.6 | G22: =('StacknRoll Strategy Analysis'!$B$2-'Sensitivity Table'!G15)*$F$6+('Hedge Ratio Analysis'!$G$22-'Hedge Ratio Analysis'!$E$22) -> 3867497.9 | H22: =('StacknRoll Strategy Analysis'!$B$2-'Sensitivity Table'!H15)*$F$6+('Hedge Ratio Analysis'!$G$22-'Hedge Ratio Analysis'!$E$22) -> 3200831.3 | I22: =('StacknRoll Strategy Analysis'!$B$2-'Sensitivity Table'!I15)*$F$6+('Hedge Ratio Analysis'!$G$22-'Hedge Ratio Analysis'!$E$22) -> 2534164.6 | J22: =('StacknRoll Strategy Analysis'!$B$2-'Sensitivity Table'!J15)*$F$6+('Hedge Ratio Analysis'!$G$22-'Hedge Ratio Analysis'!$E$22) -> 1867497.9 | ... W22: =('StacknRoll Strategy Analysis'!$B$2-'Sensitivity Table'!W15)*$F$6+('Hedge Ratio Analysis'!$G$22-'Hedge Ratio Analysis'!$E$22) -> -6799168.7
B23: 0.4 | C23: =('StacknRoll Strategy Analysis'!$B$2-'Sensitivity Table'!C15)*$F$6+('Hedge Ratio Analysis'!$G$23-'Hedge Ratio Analysis'!$E$23) -> 6515235.7 | D23: =('StacknRoll Strategy Analysis'!$B$2-'Sensitivity Table'!D15)*$F$6+('Hedge Ratio Analysis'!$G$23-'Hedge Ratio Analysis'!$E$23) -> 5848569 | E23: =('StacknRoll Strategy Analysis'!$B$2-'Sensitivity Table'!E15)*$F$6+('Hedge Ratio Analysis'!$G$23-'Hedge Ratio Analysis'!$E$23) -> 5181902.4 | F23: =('StacknRoll Strategy Analysis'!$B$2-'Sensitivity Table'!F15)*$F$6+('Hedge Ratio Analysis'!$G$23-'Hedge Ratio Analysis'!$E$23) -> 4515235.7 | G23: =('StacknRoll Strategy Analysis'!$B$2-'Sensitivity Table'!G15)*$F$6+('Hedge Ratio Analysis'!$G$23-'Hedge Ratio Analysis'!$E$23) -> 3848569 | H23: =('StacknRoll Strategy Analysis'!$B$2-'Sensitivity Table'!H15)*$F$6+('Hedge Ratio Analysis'!$G$23-'Hedge Ratio Analysis'!$E$23) -> 3181902.4 | I23: =('StacknRoll Strategy Analysis'!$B$2-'Sensitivity Table'!I15)*$F$6+('Hedge Ratio Analysis'!$G$23-'Hedge Ratio Analysis'!$E$23) -> 2515235.7 | J23: =('StacknRoll Strategy Analysis'!$B$2-'Sensitivity Table'!J15)*$F$6+('Hedge Ratio Analysis'!$G$23-'Hedge Ratio Analysis'!$E$23) -> 1848569.1 | ... W23: =('StacknRoll Strategy Analysis'!$B$2-'Sensitivity Table'!W15)*$F$6+('Hedge Ratio Analysis'!$G$23-'Hedge Ratio Analysis'!$E$23) -> -6818097.6
B24: 0.45 | C24: =('StacknRoll Strategy Analysis'!$B$2-'Sensitivity Table'!C15)*$F$6+('Hedge Ratio Analysis'!$G$24-'Hedge Ratio Analysis'!$E$24) -> 6496306.8 | D24: =('StacknRoll Strategy Analysis'!$B$2-'Sensitivity Table'!D15)*$F$6+('Hedge Ratio Analysis'!$G$24-'Hedge Ratio Analysis'!$E$24) -> 5829640.2 | E24: =('StacknRoll Strategy Analysis'!$B$2-'Sensitivity Table'!E15)*$F$6+('Hedge Ratio Analysis'!$G$24-'Hedge Ratio Analysis'!$E$24) -> 5162973.5 | F24: =('StacknRoll Strategy Analysis'!$B$2-'Sensitivity Table'!F15)*$F$6+('Hedge Ratio Analysis'!$G$24-'Hedge Ratio Analysis'!$E$24) -> 4496306.8 | G24: =('StacknRoll Strategy Analysis'!$B$2-'Sensitivity Table'!G15)*$F$6+('Hedge Ratio Analysis'!$G$24-'Hedge Ratio Analysis'!$E$24) -> 3829640.2 | H24: =('StacknRoll Strategy Analysis'!$B$2-'Sensitivity Table'!H15)*$F$6+('Hedge Ratio Analysis'!$G$24-'Hedge Ratio Analysis'!$E$24) -> 3162973.5 | I24: =('StacknRoll Strategy Analysis'!$B$2-'Sensitivity Table'!I15)*$F$6+('Hedge Ratio Analysis'!$G$24-'Hedge Ratio Analysis'!$E$24) -> 2496306.8 | J24: =('StacknRoll Strategy Analysis'!$B$2-'Sensitivity Table'!J15)*$F$6+('Hedge Ratio Analysis'!$G$24-'Hedge Ratio Analysis'!$E$24) -> 1829640.2 | ... W24: =('StacknRoll Strategy Analysis'!$B$2-'Sensitivity Table'!W15)*$F$6+('Hedge Ratio Analysis'!$G$24-'Hedge Ratio Analysis'!$E$24) -> -6837026.5
B25: 0.5 | C25: =('StacknRoll Strategy Analysis'!$B$2-'Sensitivity Table'!C15)*$F$6+('Hedge Ratio Analysis'!$G$25-'Hedge Ratio Analysis'!$E$25) -> 6477378 | D25: =('StacknRoll Strategy Analysis'!$B$2-'Sensitivity Table'!D15)*$F$6+('Hedge Ratio Analysis'!$G$25-'Hedge Ratio Analysis'!$E$25) -> 5810711.3 | E25: =('StacknRoll Strategy Analysis'!$B$2-'Sensitivity Table'!E15)*$F$6+('Hedge Ratio Analysis'!$G$25-'Hedge Ratio Analysis'!$E$25) -> 5144044.6 | F25: =('StacknRoll Strategy Analysis'!$B$2-'Sensitivity Table'!F15)*$F$6+('Hedge Ratio Analysis'!$G$25-'Hedge Ratio Analysis'!$E$25) -> 4477378 | G25: =('StacknRoll Strategy Analysis'!$B$2-'Sensitivity Table'!G15)*$F$6+('Hedge Ratio Analysis'!$G$25-'Hedge Ratio Analysis'!$E$25) -> 3810711.3 | H25: =('StacknRoll Strategy Analysis'!$B$2-'Sensitivity Table'!H15)*$F$6+('Hedge Ratio Analysis'!$G$25-'Hedge Ratio Analysis'!$E$25) -> 3144044.6 | I25: =('StacknRoll Strategy Analysis'!$B$2-'Sensitivity Table'!I15)*$F$6+('Hedge Ratio Analysis'!$G$25-'Hedge Ratio Analysis'!$E$25) -> 2477378 | J25: =('StacknRoll Strategy Analysis'!$B$2-'Sensitivity Table'!J15)*$F$6+('Hedge Ratio Analysis'!$G$25-'Hedge Ratio Analysis'!$E$25) -> 1810711.3 | ... W25: =('StacknRoll Strategy Analysis'!$B$2-'Sensitivity Table'!W15)*$F$6+('Hedge Ratio Analysis'!$G$25-'Hedge Ratio Analysis'!$E$25) -> -6855955.3
B26: 0.55 | C26: =('StacknRoll Strategy Analysis'!$B$2-'Sensitivity Table'!C15)*$F$6+('Hedge Ratio Analysis'!$G$26-'Hedge Ratio Analysis'!$E$26) -> 6458449.1 | D26: =('StacknRoll Strategy Analysis'!$B$2-'Sensitivity Table'!D15)*$F$6+('Hedge Ratio Analysis'!$G$26-'Hedge Ratio Analysis'!$E$26) -> 5791782.4 | E26: =('StacknRoll Strategy Analysis'!$B$2-'Sensitivity Table'!E15)*$F$6+('Hedge Ratio Analysis'!$G$26-'Hedge Ratio Analysis'!$E$26) -> 5125115.8 | F26: =('StacknRoll Strategy Analysis'!$B$2-'Sensitivity Table'!F15)*$F$6+('Hedge Ratio Analysis'!$G$26-'Hedge Ratio Analysis'!$E$26) -> 4458449.1 | G26: =('StacknRoll Strategy Analysis'!$B$2-'Sensitivity Table'!G15)*$F$6+('Hedge Ratio Analysis'!$G$26-'Hedge Ratio Analysis'!$E$26) -> 3791782.4 | H26: =('StacknRoll Strategy Analysis'!$B$2-'Sensitivity Table'!H15)*$F$6+('Hedge Ratio Analysis'!$G$26-'Hedge Ratio Analysis'!$E$26) -> 3125115.8 | I26: =('StacknRoll Strategy Analysis'!$B$2-'Sensitivity Table'!I15)*$F$6+('Hedge Ratio Analysis'!$G$26-'Hedge Ratio Analysis'!$E$26) -> 2458449.1 | J26: =('StacknRoll Strategy Analysis'!$B$2-'Sensitivity Table'!J15)*$F$6+('Hedge Ratio Analysis'!$G$26-'Hedge Ratio Analysis'!$E$26) -> 1791782.4 | ... W26: =('StacknRoll Strategy Analysis'!$B$2-'Sensitivity Table'!W15)*$F$6+('Hedge Ratio Analysis'!$G$26-'Hedge Ratio Analysis'!$E$26) -> -6874884.2
B27: 0.6 | C27: =('StacknRoll Strategy Analysis'!$B$2-'Sensitivity Table'!C15)*$F$6+('Hedge Ratio Analysis'!$G$27-'Hedge Ratio Analysis'!$E$27) -> 6439520.2 | D27: =('StacknRoll Strategy Analysis'!$B$2-'Sensitivity Table'!D15)*$F$6+('Hedge Ratio Analysis'!$G$27-'Hedge Ratio Analysis'!$E$27) -> 5772853.6 | E27: =('StacknRoll Strategy Analysis'!$B$2-'Sensitivity Table'!E15)*$F$6+('Hedge Ratio Analysis'!$G$27-'Hedge Ratio Analysis'!$E$27) -> 5106186.9 | F27: =('StacknRoll Strategy Analysis'!$B$2-'Sensitivity Table'!F15)*$F$6+('Hedge Ratio Analysis'!$G$27-'Hedge Ratio Analysis'!$E$27) -> 4439520.2 | G27: =('StacknRoll Strategy Analysis'!$B$2-'Sensitivity Table'!G15)*$F$6+('Hedge Ratio Analysis'!$G$27-'Hedge Ratio Analysis'!$E$27) -> 3772853.6 | H27: =('StacknRoll Strategy Analysis'!$B$2-'Sensitivity Table'!H15)*$F$6+('Hedge Ratio Analysis'!$G$27-'Hedge Ratio Analysis'!$E$27) -> 3106186.9 | I27: =('StacknRoll Strategy Analysis'!$B$2-'Sensitivity Table'!I15)*$F$6+('Hedge Ratio Analysis'!$G$27-'Hedge Ratio Analysis'!$E$27) -> 2439520.2 | J27: =('StacknRoll Strategy Analysis'!$B$2-'Sensitivity Table'!J15)*$F$6+('Hedge Ratio Analysis'!$G$27-'Hedge Ratio Analysis'!$E$27) -> 1772853.6 | ... W27: =('StacknRoll Strategy Analysis'!$B$2-'Sensitivity Table'!W15)*$F$6+('Hedge Ratio Analysis'!$G$27-'Hedge Ratio Analysis'!$E$27) -> -6893813.1
B28: 0.65 | C28: =('StacknRoll Strategy Analysis'!$B$2-'Sensitivity Table'!C15)*$F$6+('Hedge Ratio Analysis'!$G$28-'Hedge Ratio Analysis'!$E$28) -> 6420591.4 | D28: =('StacknRoll Strategy Analysis'!$B$2-'Sensitivity Table'!D15)*$F$6+('Hedge Ratio Analysis'!$G$28-'Hedge Ratio Analysis'!$E$28) -> 5753924.7 | E28: =('StacknRoll Strategy Analysis'!$B$2-'Sensitivity Table'!E15)*$F$6+('Hedge Ratio Analysis'!$G$28-'Hedge Ratio Analysis'!$E$28) -> 5087258 | F28: =('StacknRoll Strategy Analysis'!$B$2-'Sensitivity Table'!F15)*$F$6+('Hedge Ratio Analysis'!$G$28-'Hedge Ratio Analysis'!$E$28) -> 4420591.4 | G28: =('StacknRoll Strategy Analysis'!$B$2-'Sensitivity Table'!G15)*$F$6+('Hedge Ratio Analysis'!$G$28-'Hedge Ratio Analysis'!$E$28) -> 3753924.7 | H28: =('StacknRoll Strategy Analysis'!$B$2-'Sensitivity Table'!H15)*$F$6+('Hedge Ratio Analysis'!$G$28-'Hedge Ratio Analysis'!$E$28) -> 3087258 | I28: =('StacknRoll Strategy Analysis'!$B$2-'Sensitivity Table'!I15)*$F$6+('Hedge Ratio Analysis'!$G$28-'Hedge Ratio Analysis'!$E$28) -> 2420591.4 | J28: =('StacknRoll Strategy Analysis'!$B$2-'Sensitivity Table'!J15)*$F$6+('Hedge Ratio Analysis'!$G$28-'Hedge Ratio Analysis'!$E$28) -> 1753924.7 | ... W28: =('StacknRoll Strategy Analysis'!$B$2-'Sensitivity Table'!W15)*$F$6+('Hedge Ratio Analysis'!$G$28-'Hedge Ratio Analysis'!$E$28) -> -6912741.9
B29: 0.7 | C29: =('StacknRoll Strategy Analysis'!$B$2-'Sensitivity Table'!C15)*$F$6+('Hedge Ratio Analysis'!$G$29-'Hedge Ratio Analysis'!$E$29) -> 6401662.5 | D29: =('StacknRoll Strategy Analysis'!$B$2-'Sensitivity Table'!D15)*$F$6+('Hedge Ratio Analysis'!$G$29-'Hedge Ratio Analysis'!$E$29) -> 5734995.8 | E29: =('StacknRoll Strategy Analysis'!$B$2-'Sensitivity Table'!E15)*$F$6+('Hedge Ratio Analysis'!$G$29-'Hedge Ratio Analysis'!$E$29) -> 5068329.2 | F29: =('StacknRoll Strategy Analysis'!$B$2-'Sensitivity Table'!F15)*$F$6+('Hedge Ratio Analysis'!$G$29-'Hedge Ratio Analysis'!$E$29) -> 4401662.5 | G29: =('StacknRoll Strategy Analysis'!$B$2-'Sensitivity Table'!G15)*$F$6+('Hedge Ratio Analysis'!$G$29-'Hedge Ratio Analysis'!$E$29) -> 3734995.8 | H29: =('StacknRoll Strategy Analysis'!$B$2-'Sensitivity Table'!H15)*$F$6+('Hedge Ratio Analysis'!$G$29-'Hedge Ratio Analysis'!$E$29) -> 3068329.2 | I29: =('StacknRoll Strategy Analysis'!$B$2-'Sensitivity Table'!I15)*$F$6+('Hedge Ratio Analysis'!$G$29-'Hedge Ratio Analysis'!$E$29) -> 2401662.5 | J29: =('StacknRoll Strategy Analysis'!$B$2-'Sensitivity Table'!J15)*$F$6+('Hedge Ratio Analysis'!$G$29-'Hedge Ratio Analysis'!$E$29) -> 1734995.8 | ... W29: =('StacknRoll Strategy Analysis'!$B$2-'Sensitivity Table'!W15)*$F$6+('Hedge Ratio Analysis'!$G$29-'Hedge Ratio Analysis'!$E$29) -> -6931670.8
B30: 0.75 | C30: =('StacknRoll Strategy Analysis'!$B$2-'Sensitivity Table'!C15)*$F$6+('Hedge Ratio Analysis'!$G$30-'Hedge Ratio Analysis'!$E$30) -> 6382733.6 | D30: =('StacknRoll Strategy Analysis'!$B$2-'Sensitivity Table'!D15)*$F$6+('Hedge Ratio Analysis'!$G$30-'Hedge Ratio Analysis'!$E$30) -> 5716067 | E30: =('StacknRoll Strategy Analysis'!$B$2-'Sensitivity Table'!E15)*$F$6+('Hedge Ratio Analysis'!$G$30-'Hedge Ratio Analysis'!$E$30) -> 5049400.3 | F30: =('StacknRoll Strategy Analysis'!$B$2-'Sensitivity Table'!F15)*$F$6+('Hedge Ratio Analysis'!$G$30-'Hedge Ratio Analysis'!$E$30) -> 4382733.6 | G30: =('StacknRoll Strategy Analysis'!$B$2-'Sensitivity Table'!G15)*$F$6+('Hedge Ratio Analysis'!$G$30-'Hedge Ratio Analysis'!$E$30) -> 3716067 | H30: =('StacknRoll Strategy Analysis'!$B$2-'Sensitivity Table'!H15)*$F$6+('Hedge Ratio Analysis'!$G$30-'Hedge Ratio Analysis'!$E$30) -> 3049400.3 | I30: =('StacknRoll Strategy Analysis'!$B$2-'Sensitivity Table'!I15)*$F$6+('Hedge Ratio Analysis'!$G$30-'Hedge Ratio Analysis'!$E$30) -> 2382733.6 | J30: =('StacknRoll Strategy Analysis'!$B$2-'Sensitivity Table'!J15)*$F$6+('Hedge Ratio Analysis'!$G$30-'Hedge Ratio Analysis'!$E$30) -> 1716067 | ... W30: =('StacknRoll Strategy Analysis'!$B$2-'Sensitivity Table'!W15)*$F$6+('Hedge Ratio Analysis'!$G$30-'Hedge Ratio Analysis'!$E$30) -> -6950599.7
B31: 0.8 | C31: =('StacknRoll Strategy Analysis'!$B$2-'Sensitivity Table'!C15)*$F$6+('Hedge Ratio Analysis'!$G$31-'Hedge Ratio Analysis'!$E$31) -> 6363804.8 | D31: =('StacknRoll Strategy Analysis'!$B$2-'Sensitivity Table'!D15)*$F$6+('Hedge Ratio Analysis'!$G$31-'Hedge Ratio Analysis'!$E$31) -> 5697138.1 | E31: =('StacknRoll Strategy Analysis'!$B$2-'Sensitivity Table'!E15)*$F$6+('Hedge Ratio Analysis'!$G$31-'Hedge Ratio Analysis'!$E$31) -> 5030471.4 | F31: =('StacknRoll Strategy Analysis'!$B$2-'Sensitivity Table'!F15)*$F$6+('Hedge Ratio Analysis'!$G$31-'Hedge Ratio Analysis'!$E$31) -> 4363804.8 | G31: =('StacknRoll Strategy Analysis'!$B$2-'Sensitivity Table'!G15)*$F$6+('Hedge Ratio Analysis'!$G$31-'Hedge Ratio Analysis'!$E$31) -> 3697138.1 | H31: =('StacknRoll Strategy Analysis'!$B$2-'Sensitivity Table'!H15)*$F$6+('Hedge Ratio Analysis'!$G$31-'Hedge Ratio Analysis'!$E$31) -> 3030471.4 | I31: =('StacknRoll Strategy Analysis'!$B$2-'Sensitivity Table'!I15)*$F$6+('Hedge Ratio Analysis'!$G$31-'Hedge Ratio Analysis'!$E$31) -> 2363804.8 | J31: =('StacknRoll Strategy Analysis'!$B$2-'Sensitivity Table'!J15)*$F$6+('Hedge Ratio Analysis'!$G$31-'Hedge Ratio Analysis'!$E$31) -> 1697138.1 | ... W31: =('StacknRoll Strategy Analysis'!$B$2-'Sensitivity Table'!W15)*$F$6+('Hedge Ratio Analysis'!$G$31-'Hedge Ratio Analysis'!$E$31) -> -6969528.5
B32: 0.85 | C32: =('StacknRoll Strategy Analysis'!$B$2-'Sensitivity Table'!C15)*$F$6+('Hedge Ratio Analysis'!$G$32-'Hedge Ratio Analysis'!$E$32) -> 6344875.9 | D32: =('StacknRoll Strategy Analysis'!$B$2-'Sensitivity Table'!D15)*$F$6+('Hedge Ratio Analysis'!$G$32-'Hedge Ratio Analysis'!$E$32) -> 5678209.2 | E32: =('StacknRoll Strategy Analysis'!$B$2-'Sensitivity Table'!E15)*$F$6+('Hedge Ratio Analysis'!$G$32-'Hedge Ratio Analysis'!$E$32) -> 5011542.6 | F32: =('StacknRoll Strategy Analysis'!$B$2-'Sensitivity Table'!F15)*$F$6+('Hedge Ratio Analysis'!$G$32-'Hedge Ratio Analysis'!$E$32) -> 4344875.9 | G32: =('StacknRoll Strategy Analysis'!$B$2-'Sensitivity Table'!G15)*$F$6+('Hedge Ratio Analysis'!$G$32-'Hedge Ratio Analysis'!$E$32) -> 3678209.2 | H32: =('StacknRoll Strategy Analysis'!$B$2-'Sensitivity Table'!H15)*$F$6+('Hedge Ratio Analysis'!$G$32-'Hedge Ratio Analysis'!$E$32) -> 3011542.6 | I32: =('StacknRoll Strategy Analysis'!$B$2-'Sensitivity Table'!I15)*$F$6+('Hedge Ratio Analysis'!$G$32-'Hedge Ratio Analysis'!$E$32) -> 2344875.9 | J32: =('StacknRoll Strategy Analysis'!$B$2-'Sensitivity Table'!J15)*$F$6+('Hedge Ratio Analysis'!$G$32-'Hedge Ratio Analysis'!$E$32) -> 1678209.2 | ... W32: =('StacknRoll Strategy Analysis'!$B$2-'Sensitivity Table'!W15)*$F$6+('Hedge Ratio Analysis'!$G$32-'Hedge Ratio Analysis'!$E$32) -> -6988457.4
B33: 0.9 | C33: =('StacknRoll Strategy Analysis'!$B$2-'Sensitivity Table'!C15)*$F$6+('Hedge Ratio Analysis'!$G$33-'Hedge Ratio Analysis'!$E$33) -> 6325947 | D33: =('StacknRoll Strategy Analysis'!$B$2-'Sensitivity Table'!D15)*$F$6+('Hedge Ratio Analysis'!$G$33-'Hedge Ratio Analysis'!$E$33) -> 5659280.4 | E33: =('StacknRoll Strategy Analysis'!$B$2-'Sensitivity Table'!E15)*$F$6+('Hedge Ratio Analysis'!$G$33-'Hedge Ratio Analysis'!$E$33) -> 4992613.7 | F33: =('StacknRoll Strategy Analysis'!$B$2-'Sensitivity Table'!F15)*$F$6+('Hedge Ratio Analysis'!$G$33-'Hedge Ratio Analysis'!$E$33) -> 4325947 | G33: =('StacknRoll Strategy Analysis'!$B$2-'Sensitivity Table'!G15)*$F$6+('Hedge Ratio Analysis'!$G$33-'Hedge Ratio Analysis'!$E$33) -> 3659280.4 | H33: =('StacknRoll Strategy Analysis'!$B$2-'Sensitivity Table'!H15)*$F$6+('Hedge Ratio Analysis'!$G$33-'Hedge Ratio Analysis'!$E$33) -> 2992613.7 | I33: =('StacknRoll Strategy Analysis'!$B$2-'Sensitivity Table'!I15)*$F$6+('Hedge Ratio Analysis'!$G$33-'Hedge Ratio Analysis'!$E$33) -> 2325947 | J33: =('StacknRoll Strategy Analysis'!$B$2-'Sensitivity Table'!J15)*$F$6+('Hedge Ratio Analysis'!$G$33-'Hedge Ratio Analysis'!$E$33) -> 1659280.4 | ... W33: =('StacknRoll Strategy Analysis'!$B$2-'Sensitivity Table'!W15)*$F$6+('Hedge Ratio Analysis'!$G$33-'Hedge Ratio Analysis'!$E$33) -> -7007386.3
B34: 0.95 | C34: =('StacknRoll Strategy Analysis'!$B$2-'Sensitivity Table'!C15)*$F$6+('Hedge Ratio Analysis'!$G$34-'Hedge Ratio Analysis'!$E$34) -> 6307018.2 | D34: =('StacknRoll Strategy Analysis'!$B$2-'Sensitivity Table'!D15)*$F$6+('Hedge Ratio Analysis'!$G$34-'Hedge Ratio Analysis'!$E$34) -> 5640351.5 | E34: =('StacknRoll Strategy Analysis'!$B$2-'Sensitivity Table'!E15)*$F$6+('Hedge Ratio Analysis'!$G$34-'Hedge Ratio Analysis'!$E$34) -> 4973684.8 | F34: =('StacknRoll Strategy Analysis'!$B$2-'Sensitivity Table'!F15)*$F$6+('Hedge Ratio Analysis'!$G$34-'Hedge Ratio Analysis'!$E$34) -> 4307018.2 | G34: =('StacknRoll Strategy Analysis'!$B$2-'Sensitivity Table'!G15)*$F$6+('Hedge Ratio Analysis'!$G$34-'Hedge Ratio Analysis'!$E$34) -> 3640351.5 | H34: =('StacknRoll Strategy Analysis'!$B$2-'Sensitivity Table'!H15)*$F$6+('Hedge Ratio Analysis'!$G$34-'Hedge Ratio Analysis'!$E$34) -> 2973684.8 | I34: =('StacknRoll Strategy Analysis'!$B$2-'Sensitivity Table'!I15)*$F$6+('Hedge Ratio Analysis'!$G$34-'Hedge Ratio Analysis'!$E$34) -> 2307018.2 | J34: =('StacknRoll Strategy Analysis'!$B$2-'Sensitivity Table'!J15)*$F$6+('Hedge Ratio Analysis'!$G$34-'Hedge Ratio Analysis'!$E$34) -> 1640351.5 | ... W34: =('StacknRoll Strategy Analysis'!$B$2-'Sensitivity Table'!W15)*$F$6+('Hedge Ratio Analysis'!$G$34-'Hedge Ratio Analysis'!$E$34) -> -7026315.1
B35: 1 | C35: =('StacknRoll Strategy Analysis'!$B$2-'Sensitivity Table'!C15)*$F$6+('Hedge Ratio Analysis'!$G$35-'Hedge Ratio Analysis'!$E$35) -> 6288089.3 | D35: =('StacknRoll Strategy Analysis'!$B$2-'Sensitivity Table'!D15)*$F$6+('Hedge Ratio Analysis'!$G$35-'Hedge Ratio Analysis'!$E$35) -> 5621422.6 | E35: =('StacknRoll Strategy Analysis'!$B$2-'Sensitivity Table'!E15)*$F$6+('Hedge Ratio Analysis'!$G$35-'Hedge Ratio Analysis'!$E$35) -> 4954756 | F35: =('StacknRoll Strategy Analysis'!$B$2-'Sensitivity Table'!F15)*$F$6+('Hedge Ratio Analysis'!$G$35-'Hedge Ratio Analysis'!$E$35) -> 4288089.3 | G35: =('StacknRoll Strategy Analysis'!$B$2-'Sensitivity Table'!G15)*$F$6+('Hedge Ratio Analysis'!$G$35-'Hedge Ratio Analysis'!$E$35) -> 3621422.6 | H35: =('StacknRoll Strategy Analysis'!$B$2-'Sensitivity Table'!H15)*$F$6+('Hedge Ratio Analysis'!$G$35-'Hedge Ratio Analysis'!$E$35) -> 2954756 | I35: =('StacknRoll Strategy Analysis'!$B$2-'Sensitivity Table'!I15)*$F$6+('Hedge Ratio Analysis'!$G$35-'Hedge Ratio Analysis'!$E$35) -> 2288089.3 | J35: =('StacknRoll Strategy Analysis'!$B$2-'Sensitivity Table'!J15)*$F$6+('Hedge Ratio Analysis'!$G$35-'Hedge Ratio Analysis'!$E$35) -> 1621422.6 | ... W35: =('StacknRoll Strategy Analysis'!$B$2-'Sensitivity Table'!W15)*$F$6+('Hedge Ratio Analysis'!$G$35-'Hedge Ratio Analysis'!$E$35) -> -7045244
